Workbook

Sheet 0. Instrucciones
A1: Diagnóstico de Madurez Tecnológica/Digital - Fase 2
A2: Cátedra Sistemas de Información - Universidad EAFIT
A4: Qué es este libro
A5: Este archivo reemplaza el diligenciamiento aislado del diagnóstico externo y complementa el Excel 'Automatización de Procesos'. Mide la madurez de la empresa analizada en 7 dimensiones (36 indicadores), calcula automáticamente brechas frente a un nivel objetivo, y las prioriza en una hoja de ruta trazable.
A7: Cómo se diligencia
A8: 1. En la pestaña 'Datos Empresa' complete la información general (una sola vez).
A9: 2. En la pestaña 'Diagnóstico (36 indicadores)' califique cada indicador de 1 a 5 usando la lista desplegable de la columna Calificación, apoyándose en la rúbrica de las columnas de referencia. Adjunte o describa la evidencia que sustenta la calificación (columna Evidencia) - sin evidencia, no califique por encima de nivel 2. Ajuste el Nivel Objetivo si el equipo, junto con la empresa, decide una meta distinta a 4.
A10: 3. 'Resultados por Dimensión' se calcula solo (no editar las fórmulas); solo puede ajustar la columna Peso si el equipo decide reponderar dimensiones (la suma de pesos debe seguir siendo 100%).
A11: 4. 'Radar y Dashboard' se actualiza solo con lo anterior.
A12: 5. En 'Brechas y Priorización' registre el Esfuerzo estimado (1-5) de cerrar cada brecha; la prioridad se calcula sola.
A13: 6. En 'Iniciativas y Hoja de Ruta' redacte una iniciativa concreta por cada brecha priorizada y de seguimiento a su estado.
A15: Escala de madurez (1 a 5), común a las 7 dimensiones
... A22: Celdas de color amarillo = usted debe diligenciarlas. Celdas en blanco con fórmula = no editar.

Sheet 1. Datos Empresa
A1: Datos de la Empresa Analizada
A2: Nombre de la empresa | B2: UNIVERSIDAD EAFIT
A3: Sector / industria | B3: EDUCACIÓN
A4: Tamaño (No. empleados) | B4: 2800 APROX
A5: Ciudad | B5: MEDELLIN
A6: Contacto en la empresa | B6: Infraestructura TI – Redes Juan Acevedo
A7: Cargo del contacto | B7: Equipo de Infraestructura TI / Redes
A8: Equipo (integrantes) | B8: 4 integrantes
A9: Fecha de diagnóstico | B9: 46310

Sheet 2. Diagnóstico
A1: ID | B1: Dimensión | C1: Subdimensión | D1: Indicador (pregunta) | E1: Rúbrica Nivel 1 | F1: Rúbrica Nivel 3 | G1: Rúbrica Nivel 5 | H1: Calificación (1-5) | I1: Evidencia / validación requerida | J1: Nivel Objetivo (1-5) | K1: Brecha
A2: D01 | B2: 1. Estrategia y Gobierno de TI | C2: Alineación estratégica | D2: Qué tan explícitamente se deriva la estrategia tecnológica de la estrategia de negocio? | E2: No existe estrategia de TI escrita | F2: Existe un plan de TI, pero no referencia objetivos de negocio | G2: El plan de TI se deriva y revisa formalmente contra la estrategia de negocio | H2: 4 | I2: Solicitar plan estratégico de TI y mapa de alineación con objetivos institucionales; adjuntar versión vigente y acta de revisión. | J2: 4 | K2: =IF(H2="","",J2-H2)
A3: D02 | B3: 1. Estrategia y Gobierno de TI | C3: Patrocinio ejecutivo | D3: Existe patrocinio activo de la alta dirección para iniciativas tecnologicas? | E3: La dirección no participa ni prioriza iniciativas de TI | F3: La dirección aprueba presupuesto pero no hace seguimiento | G3: La dirección patrocina, prioriza y hace seguimiento periódico de iniciativas clave | H3: 4 | I3: Validar actas de comité/directivos y seguimiento a iniciativas TI; registrar frecuencia y responsables. | J3: 4 | K3: =IF(H3="","",J3-H3) -> 0
A4: D03 | B4: 1. Estrategia y Gobierno de TI | C4: Gobierno de decisiones | D4: Existe una instancia formal (comité) que decide inversión en tecnología? | E4: Las decisiones de TI las toma una sola persona de forma informal | F4: Existen reuniones esporadicas sin reglas claras de decisión | G4: Existe un comité formal con reglas y calendario definidos | H4: 4 | I4: Solicitar acta, integrantes, periodicidad y reglas de decisión del comité de tecnología. | J4: 4 | K4: =IF(H4="","",J4-H4) -> 0
A5: D04 | B5: 1. Estrategia y Gobierno de TI | C5: Priorización de inversión | D5: Las inversiones en TI se priorizan con criterios de negocio documentados? | E5: Se invierte por urgencia o intuición | F5: Existen criterios informales, no siempre aplicados | G5: Existe un método documentado de priorización (ej. impacto/esfuerzo, ROI) | H5: 4 | I5: Revisar matriz de priorización de inversiones TI (impacto, riesgo, costo, beneficio) y ejemplos recientes. | J5: 4 | K5: =IF(H5="","",J5-H5) -> 0
A6: D05 | B6: 1. Estrategia y Gobierno de TI | C6: Medición de valor | D6: Se mide el retorno o beneficio de las iniciativas tecnologicas ya implementadas? | E6: No se mide el resultado de lo implementado | F6: Se mide de forma anecdótica, sin indicadores fijos | G6: Existen indicadores definidos y se revisan tras cada iniciativa | H6: 4 | I6: Solicitar indicadores de beneficio/ROI y evaluaciones posteriores a proyectos implementados. | J6: 4 | K6: =IF(H6="","",J6-H6) -> 0
A7: D06 | B7: 2. Procesos y Operación | C7: Documentación de procesos | D7: Los procesos clave están documentados o diagramados (BPMN u otro)? | E7: No hay documentación de procesos | F7: Algunos procesos están documentados, desactualizados o incompletos | G7: Los procesos clave están documentados, vigentes y accesibles | H7: 4 | I7: Revisar catálogo de procesos, procedimientos o diagramas vigentes y repositorio donde están publicados. | J7: 4 | K7: =IF(H7="","",J7-H7) -> 0
A8: D07 | B8: 2. Procesos y Operación | C8: Estandarización | D8: Los procesos se ejecutan de manera estandarizada entre áreas, turnos o personas? | E8: Cada persona ejecuta el proceso a su manera | F8: Existe un estándar, pero se aplica de forma desigual | G8: El proceso se ejecuta igual sin importar quién lo realice | H8: 3 | I8: Contrastar procedimientos de soporte y operación entre equipos; verificar control de versiones y cumplimiento. | J8: 4 | K8: =IF(H8="","",J8-H8) -> 1
A9: D08 | B9: 2. Procesos y Operación | C9: Automatización | D9: Qué proporción de los procesos clave tiene algún grado de automatización (RPA, BPM, workflow)? | E9: Ningún proceso clave está automatizado | F9: Automatización puntual en 1-2 procesos | G9: Automatización extendida en la mayoría de procesos clave | H9: 3 | I9: Inventariar procesos con automatización (flujos, scripts, RPA/BPM) y evidencia de uso en producción. | J9: 4 | K9: =IF(H9="","",J9-H9) -> 1
A10: D09 | B10: 2. Procesos y Operación | C10: Eficiencia operativa | D10: Se miden tiempos de ciclo y cuellos de botella de los procesos? | E10: No se miden tiempos ni cuellos de botella | F10: Se miden de forma manual y ocasional | G10: Se miden de forma sistemática con indicadores de ciclo | H10: 2 | I10: No se aportó evidencia específica. Solicitar métricas de tiempos de atención/resolución, SLA, backlog y cuellos de botella. | J10: 4 | K10: =IF(H10="","",J10-H10) -> 2
A11: D10 | B11: 2. Procesos y Operación | C11: Mejora continua | D11: Existe un mecanismo formal de mejora continua de procesos? | E11: No existe mecanismo de mejora continua | F11: Se hacen mejoras reactivas ante problemas | G11: Existe un ciclo formal de mejora continua (ej. retro periódica) | H11: 3 | I11: Solicitar registro de mejoras, retrospectivas, acciones correctivas y seguimiento periódico. | J11: 4 | K11: =IF(H11="","",J11-H11) -> 1
A12: D11 | B12: 3. Datos, Analítica e IA | C12: Gobierno de datos | D12: Existe responsable o politica de datos en la organización? | E12: No hay responsable ni politica de datos | F12: Hay dueno de datos por area, sin politica escrita | G12: Existe politica de datos, catálogo y metricas de calidad monitoreadas | H12: 4 | I12: Validar política de gobierno de datos, responsables por dominio, catálogo y controles de calidad. | J12: 4 | K12: =IF(H12="","",J12-H12) -> 0
A13: D12 | B13: 3. Datos, Analítica e IA | C13: Calidad de datos | D13: Se mide y gestiona la calidad de los datos (duplicados, completitud, exactitud)? | E13: No se mide la calidad de los datos | F13: Se detectan problemas de calidad de forma reactiva | G13: Se mide y gestiona la calidad de datos de forma proactiva | H13: 2 | I13: No se aportó evidencia específica. Solicitar reportes de duplicados, completitud, exactitud y responsables de remediación. | J13: 4 | K13: =IF(H13="","",J13-H13) -> 2
... A37: D36 | B37: 7. Experiencia Digital | C37: Autoservicio | D37: Los clientes pueden autogestionar solicitudes sin intervención humana? | E37: Toda solicitud requiere intervención humana | F37: Autoservicio disponible para solicitudes simples | G37: Autoservicio disponible para la mayoría de solicitudes | H37: 3 | I37: Inventariar trámites con autoservicio, porcentaje de solicitudes autogestionadas y excepciones que requieren atención humana. | J37: 4 | K37: =IF(H37="","",J37-H37) -> 1

Sheet 3. Resultados x Dimensión
A1: Dimensión | B1: Peso | C1: Promedio Actual | D1: Promedio Objetivo | E1: Brecha Dimensión | F1: Contribución Ponderada
A2: 1. Estrategia y Gobierno de TI | B2: 0.15 | C2: =IFERROR(AVERAGEIF('2. Diagnóstico'!$B$2:$B$37,$A2,'2. Diagnóstico'!$H$2:$H$37),"") -> 4 | D2: =IFERROR(AVERAGEIF('2. Diagnóstico'!$B$2:$B$37,$A2,'2. Diagnóstico'!$J$2:$J$37),"") -> 4 | E2: =IF(OR(C2="",D2=""),"",D2-C2) -> 0 | F2: =IF(C2="",0,C2*B2) -> 0.6
A3: 2. Procesos y Operación | B3: 0.15 | C3: =IFERROR(AVERAGEIF('2. Diagnóstico'!$B$2:$B$37,$A3,'2. Diagnóstico'!$H$2:$H$37),"") -> 3 | D3: =IFERROR(AVERAGEIF('2. Diagnóstico'!$B$2:$B$37,$A3,'2. Diagnóstico'!$J$2:$J$37),"") -> 4 | E3: =IF(OR(C3="",D3=""),"",D3-C3) -> 1 | F3: =IF(C3="",0,C3*B3) -> 0.45
A4: 3. Datos, Analítica e IA | B4: 0.2 | C4: =IFERROR(AVERAGEIF('2. Diagnóstico'!$B$2:$B$37,$A4,'2. Diagnóstico'!$H$2:$H$37),"") -> 3.8333333 | D4: =IFERROR(AVERAGEIF('2. Diagnóstico'!$B$2:$B$37,$A4,'2. Diagnóstico'!$J$2:$J$37),"") -> 4 | E4: =IF(OR(C4="",D4=""),"",D4-C4) -> 0.16666667 | F4: =IF(C4="",0,C4*B4) -> 0.76666667
A5: 4. Arquitectura e Integración | B5: 0.15 | C5: =IFERROR(AVERAGEIF('2. Diagnóstico'!$B$2:$B$37,$A5,'2. Diagnóstico'!$H$2:$H$37),"") -> 4.2 | D5: =IFERROR(AVERAGEIF('2. Diagnóstico'!$B$2:$B$37,$A5,'2. Diagnóstico'!$J$2:$J$37),"") -> 4 | E5: =IF(OR(C5="",D5=""),"",D5-C5) -> -0.2 | F5: =IF(C5="",0,C5*B5) -> 0.63
A6: 5. Ciberseguridad y Riesgo | B6: 0.15 | C6: =IFERROR(AVERAGEIF('2. Diagnóstico'!$B$2:$B$37,$A6,'2. Diagnóstico'!$H$2:$H$37),"") -> 3.8 | D6: =IFERROR(AVERAGEIF('2. Diagnóstico'!$B$2:$B$37,$A6,'2. Diagnóstico'!$J$2:$J$37),"") -> 4 | E6: =IF(OR(C6="",D6=""),"",D6-C6) -> 0.2 | F6: =IF(C6="",0,C6*B6) -> 0.57
A7: 6. Cultura, Talento y Gestión del Cambio | B7: 0.1 | C7: =IFERROR(AVERAGEIF('2. Diagnóstico'!$B$2:$B$37,$A7,'2. Diagnóstico'!$H$2:$H$37),"") -> 3.4 | D7: =IFERROR(AVERAGEIF('2. Diagnóstico'!$B$2:$B$37,$A7,'2. Diagnóstico'!$J$2:$J$37),"") -> 4 | E7: =IF(OR(C7="",D7=""),"",D7-C7) -> 0.6 | F7: =IF(C7="",0,C7*B7) -> 0.34
A8: 7. Experiencia Digital | B8: 0.1 | C8: =IFERROR(AVERAGEIF('2. Diagnóstico'!$B$2:$B$37,$A8,'2. Diagnóstico'!$H$2:$H$37),"") -> 3.4 | D8: =IFERROR(AVERAGEIF('2. Diagnóstico'!$B$2:$B$37,$A8,'2. Diagnóstico'!$J$2:$J$37),"") -> 4 | E8: =IF(OR(C8="",D8=""),"",D8-C8) -> 0.6 | F8: =IF(C8="",0,C8*B8) -> 0.34
A9: TOTAL / PUNTAJE GLOBAL | B9: =SUM(B2:B8) -> 1 | F9: =SUM(F2:F8) -> 3.6966667
A11: Nivel de madurez global: | B11: =IF(F9=0,"Sin datos",IF(F9<1.5,"1 - Inicial",IF(F9<2.5,"2 - Emergente",IF(F9<3.5,"3 - Definido",IF(F9<4.5,"4 - Gestionado","5 - Optimizado"))))) -> 4 - Gestionado

Sheet 4. Radar y Dashboard
A1: Dashboard Ejecutivo de Madurez
A3: Puntaje Global | C3: Nivel de Madurez | F3: Dimensión más fuerte | I3: Top 5 Brechas Prioritarias
A4: ='3. Resultados x Dimensión'!F9 -> 3.6966667 | C4: ='3. Resultados x Dimensión'!B11 -> 4 - Gestionado | F4: =IFERROR(INDEX('3. Resultados x Dimensión'!A2:A8,MATCH(MAX('3. Resultados x Dimensión'!C2:C8),'3. Resultados x Dimensión'!C2:C8,0)),"Sin datos") -> 4. Arquitectura e Integración | I4: Indicador | J4: Dimensión | K4: Brecha
A5: Brechas críticas (>=3 pts) | F5: Dimensión más debil | I5: =IFERROR(INDEX('5. Brechas y Priorización'!$C$2:$C$37,MATCH(1,'5. Brechas y Priorización'!$G$2:$G$37,0)),"") -> Se miden tiempos de ciclo y cuellos de botella de los procesos? | J5: =IFERROR(INDEX('5. Brechas y Priorización'!$B$2:$B$37,MATCH(1,'5. Brechas y Priorización'!$G$2:$G$37,0)),"") -> 2. Procesos y Operación | K5: =IFERROR(INDEX('5. Brechas y Priorización'!$D$2:$D$37,MATCH(1,'5. Brechas y Priorización'!$G$2:$G$37,0)),"") -> 2
A6: =COUNTIF('5. Brechas y Priorización'!D2:D37,">=3") -> 0 | F6: =IFERROR(INDEX('3. Resultados x Dimensión'!A2:A8,MATCH(MIN('3. Resultados x Dimensión'!C2:C8),'3. Resultados x Dimensión'!C2:C8,0)),"Sin datos") -> 2. Procesos y Operación | I6: =IFERROR(INDEX('5. Brechas y Priorización'!$C$2:$C$37,MATCH(2,'5. Brechas y Priorización'!$G$2:$G$37,0)),"") -> Se mide y gestiona la calidad de los datos (duplicados, completitud, exactitud)? | J6: =IFERROR(INDEX('5. Brechas y Priorización'!$B$2:$B$37,MATCH(2,'5. Brechas y Priorización'!$G$2:$G$37,0)),"") -> 3. Datos, Analítica e IA | K6: =IFERROR(INDEX('5. Brechas y Priorización'!$D$2:$D$37,MATCH(2,'5. Brechas y Priorización'!$G$2:$G$37,0)),"") -> 2
A7: Dimensión | B7: Actual | C7: Objetivo | E7: Brecha | I7: =IFERROR(INDEX('5. Brechas y Priorización'!$C$2:$C$37,MATCH(3,'5. Brechas y Priorización'!$G$2:$G$37,0)),"") -> Los procesos se ejecutan de manera estandarizada entre áreas, turnos o personas? | J7: =IFERROR(INDEX('5. Brechas y Priorización'!$B$2:$B$37,MATCH(3,'5. Brechas y Priorización'!$G$2:$G$37,0)),"") -> 2. Procesos y Operación | K7: =IFERROR(INDEX('5. Brechas y Priorización'!$D$2:$D$37,MATCH(3,'5. Brechas y Priorización'!$G$2:$G$37,0)),"") -> 1
A8: ='3. Resultados x Dimensión'!A2 -> 1. Estrategia y Gobierno de TI | B8: ='3. Resultados x Dimensión'!C2 -> 4 | C8: ='3. Resultados x Dimensión'!D2 -> 4 | E8: ='3. Resultados x Dimensión'!E2 -> 0 | I8: =IFERROR(INDEX('5. Brechas y Priorización'!$C$2:$C$37,MATCH(4,'5. Brechas y Priorización'!$G$2:$G$37,0)),"") -> Qué proporción de los procesos clave tiene algún grado de automatización (RPA, BPM, workflow)? | J8: =IFERROR(INDEX('5. Brechas y Priorización'!$B$2:$B$37,MATCH(4,'5. Brechas y Priorización'!$G$2:$G$37,0)),"") -> 2. Procesos y Operación | K8: =IFERROR(INDEX('5. Brechas y Priorización'!$D$2:$D$37,MATCH(4,'5. Brechas y Priorización'!$G$2:$G$37,0)),"") -> 1
A9: ='3. Resultados x Dimensión'!A3 -> 2. Procesos y Operación | B9: ='3. Resultados x Dimensión'!C3 -> 3 | C9: ='3. Resultados x Dimensión'!D3 -> 4 | E9: ='3. Resultados x Dimensión'!E3 -> 1 | I9: =IFERROR(INDEX('5. Brechas y Priorización'!$C$2:$C$37,MATCH(5,'5. Brechas y Priorización'!$G$2:$G$37,0)),"") -> Existe un mecanismo formal de mejora continua de procesos? | J9: =IFERROR(INDEX('5. Brechas y Priorización'!$B$2:$B$37,MATCH(5,'5. Brechas y Priorización'!$G$2:$G$37,0)),"") -> 2. Procesos y Operación | K9: =IFERROR(INDEX('5. Brechas y Priorización'!$D$2:$D$37,MATCH(5,'5. Brechas y Priorización'!$G$2:$G$37,0)),"") -> 1
A10: ='3. Resultados x Dimensión'!A4 -> 3. Datos, Analítica e IA | B10: ='3. Resultados x Dimensión'!C4 -> 3.8333333 | C10: ='3. Resultados x Dimensión'!D4 -> 4 | E10: ='3. Resultados x Dimensión'!E4 -> 0.16666667
A11: ='3. Resultados x Dimensión'!A5 -> 4. Arquitectura e Integración | B11: ='3. Resultados x Dimensión'!C5 -> 4.2 | C11: ='3. Resultados x Dimensión'!D5 -> 4 | E11: ='3. Resultados x Dimensión'!E5 -> -0.2
A12: ='3. Resultados x Dimensión'!A6 -> 5. Ciberseguridad y Riesgo | B12: ='3. Resultados x Dimensión'!C6 -> 3.8 | C12: ='3. Resultados x Dimensión'!D6 -> 4 | E12: ='3. Resultados x Dimensión'!E6 -> 0.2
A13: ='3. Resultados x Dimensión'!A7 -> 6. Cultura, Talento y Gestión del Cambio | B13: ='3. Resultados x Dimensión'!C7 -> 3.4 | C13: ='3. Resultados x Dimensión'!D7 -> 4 | E13: ='3. Resultados x Dimensión'!E7 -> 0.6
A14: ='3. Resultados x Dimensión'!A8 -> 7. Experiencia Digital | B14: ='3. Resultados x Dimensión'!C8 -> 3.4 | C14: ='3. Resultados x Dimensión'!D8 -> 4 | E14: ='3. Resultados x Dimensión'!E8 -> 0.6

Sheet 5. Brechas y Priorización
A1: ID | B1: Dimensión | C1: Indicador | D1: Brecha (Impacto) | E1: Esfuerzo (1-5) | F1: Prioridad | G1: Rank Brecha | I1: Top 10 Brechas (GAP) por Indicador
A2: =IF('2. Diagnóstico'!A2="","",'2. Diagnóstico'!A2) -> D01 | B2: =IF('2. Diagnóstico'!B2="","",'2. Diagnóstico'!B2) -> 1. Estrategia y Gobierno de TI | C2: =IF('2. Diagnóstico'!D2="","",'2. Diagnóstico'!D2) -> Qué tan explícitamente se deriva la estrategia tecnológica de la estrategia de negocio? | D2: =IF('2. Diagnóstico'!K2="","",'2. Diagnóstico'!K2) | F2: =IF(OR(D2="",E2=""),"",IF(AND(D2>=3,E2<=2),"Corto plazo",IF(AND(D2>=3,E2>2),"Mediano/Largo plazo",IF(D2<=0,"Sin brecha","Baja prioridad")))) | G2: =IF(D2="","",RANK(D2,$D$2:$D$37)+COUNTIF($D$2:D2,D2)-1) | I2: Indicador | J2: Dimensión | K2: Brecha
A3: =IF('2. Diagnóstico'!A3="","",'2. Diagnóstico'!A3) -> D02 | B3: =IF('2. Diagnóstico'!B3="","",'2. Diagnóstico'!B3) -> 1. Estrategia y Gobierno de TI | C3: =IF('2. Diagnóstico'!D3="","",'2. Diagnóstico'!D3) -> Existe patrocinio activo de la alta dirección para iniciativas tecnologicas? | D3: =IF('2. Diagnóstico'!K3="","",'2. Diagnóstico'!K3) -> 0 | F3: =IF(OR(D3="",E3=""),"",IF(AND(D3>=3,E3<=2),"Corto plazo",IF(AND(D3>=3,E3>2),"Mediano/Largo plazo",IF(D3<=0,"Sin brecha","Baja prioridad")))) | G3: =IF(D3="","",RANK(D3,$D$2:$D$37)+COUNTIF($D$2:D3,D3)-1) -> 14 | I3: =IFERROR(INDEX($C$2:$C$37,MATCH(1,$G$2:$G$37,0)),"") -> Se miden tiempos de ciclo y cuellos de botella de los procesos? | J3: =IFERROR(INDEX($B$2:$B$37,MATCH(1,$G$2:$G$37,0)),"") -> 2. Procesos y Operación | K3: =IFERROR(INDEX($D$2:$D$37,MATCH(1,$G$2:$G$37,0)),"") -> 2
A4: =IF('2. Diagnóstico'!A4="","",'2. Diagnóstico'!A4) -> D03 | B4: =IF('2. Diagnóstico'!B4="","",'2. Diagnóstico'!B4) -> 1. Estrategia y Gobierno de TI | C4: =IF('2. Diagnóstico'!D4="","",'2. Diagnóstico'!D4) -> Existe una instancia formal (comité) que decide inversión en tecnología? | D4: =IF('2. Diagnóstico'!K4="","",'2. Diagnóstico'!K4) -> 0 | F4: =IF(OR(D4="",E4=""),"",IF(AND(D4>=3,E4<=2),"Corto plazo",IF(AND(D4>=3,E4>2),"Mediano/Largo plazo",IF(D4<=0,"Sin brecha","Baja prioridad")))) | G4: =IF(D4="","",RANK(D4,$D$2:$D$37)+COUNTIF($D$2:D4,D4)-1) -> 15 | I4: =IFERROR(INDEX($C$2:$C$37,MATCH(2,$G$2:$G$37,0)),"") -> Se mide y gestiona la calidad de los datos (duplicados, completitud, exactitud)? | J4: =IFERROR(INDEX($B$2:$B$37,MATCH(2,$G$2:$G$37,0)),"") -> 3. Datos, Analítica e IA | K4: =IFERROR(INDEX($D$2:$D$37,MATCH(2,$G$2:$G$37,0)),"") -> 2
A5: =IF('2. Diagnóstico'!A5="","",'2. Diagnóstico'!A5) -> D04 | B5: =IF('2. Diagnóstico'!B5="","",'2. Diagnóstico'!B5) -> 1. Estrategia y Gobierno de TI | C5: =IF('2. Diagnóstico'!D5="","",'2. Diagnóstico'!D5) -> Las inversiones en TI se priorizan con criterios de negocio documentados? | D5: =IF('2. Diagnóstico'!K5="","",'2. Diagnóstico'!K5) -> 0 | F5: =IF(OR(D5="",E5=""),"",IF(AND(D5>=3,E5<=2),"Corto plazo",IF(AND(D5>=3,E5>2),"Mediano/Largo plazo",IF(D5<=0,"Sin brecha","Baja prioridad")))) | G5: =IF(D5="","",RANK(D5,$D$2:$D$37)+COUNTIF($D$2:D5,D5)-1) -> 16 | I5: =IFERROR(INDEX($C$2:$C$37,MATCH(3,$G$2:$G$37,0)),"") -> Los procesos se ejecutan de manera estandarizada entre áreas, turnos o personas? | J5: =IFERROR(INDEX($B$2:$B$37,MATCH(3,$G$2:$G$37,0)),"") -> 2. Procesos y Operación | K5: =IFERROR(INDEX($D$2:$D$37,MATCH(3,$G$2:$G$37,0)),"") -> 1
A6: =IF('2. Diagnóstico'!A6="","",'2. Diagnóstico'!A6) -> D05 | B6: =IF('2. Diagnóstico'!B6="","",'2. Diagnóstico'!B6) -> 1. Estrategia y Gobierno de TI | C6: =IF('2. Diagnóstico'!D6="","",'2. Diagnóstico'!D6) -> Se mide el retorno o beneficio de las iniciativas tecnologicas ya implementadas? | D6: =IF('2. Diagnóstico'!K6="","",'2. Diagnóstico'!K6) -> 0 | F6: =IF(OR(D6="",E6=""),"",IF(AND(D6>=3,E6<=2),"Corto plazo",IF(AND(D6>=3,E6>2),"Mediano/Largo plazo",IF(D6<=0,"Sin brecha","Baja prioridad")))) | G6: =IF(D6="","",RANK(D6,$D$2:$D$37)+COUNTIF($D$2:D6,D6)-1) -> 17 | I6: =IFERROR(INDEX($C$2:$C$37,MATCH(4,$G$2:$G$37,0)),"") -> Qué proporción de los procesos clave tiene algún grado de automatización (RPA, BPM, workflow)? | J6: =IFERROR(INDEX($B$2:$B$37,MATCH(4,$G$2:$G$37,0)),"") -> 2. Procesos y Operación | K6: =IFERROR(INDEX($D$2:$D$37,MATCH(4,$G$2:$G$37,0)),"") -> 1
A7: =IF('2. Diagnóstico'!A7="","",'2. Diagnóstico'!A7) -> D06 | B7: =IF('2. Diagnóstico'!B7="","",'2. Diagnóstico'!B7) -> 2. Procesos y Operación | C7: =IF('2. Diagnóstico'!D7="","",'2. Diagnóstico'!D7) -> Los procesos clave están documentados o diagramados (BPMN u otro)? | D7: =IF('2. Diagnóstico'!K7="","",'2. Diagnóstico'!K7) -> 0 | F7: =IF(OR(D7="",E7=""),"",IF(AND(D7>=3,E7<=2),"Corto plazo",IF(AND(D7>=3,E7>2),"Mediano/Largo plazo",IF(D7<=0,"Sin brecha","Baja prioridad")))) | G7: =IF(D7="","",RANK(D7,$D$2:$D$37)+COUNTIF($D$2:D7,D7)-1) -> 18 | I7: =IFERROR(INDEX($C$2:$C$37,MATCH(5,$G$2:$G$37,0)),"") -> Existe un mecanismo formal de mejora continua de procesos? | J7: =IFERROR(INDEX($B$2:$B$37,MATCH(5,$G$2:$G$37,0)),"") -> 2. Procesos y Operación | K7: =IFERROR(INDEX($D$2:$D$37,MATCH(5,$G$2:$G$37,0)),"") -> 1
A8: =IF('2. Diagnóstico'!A8="","",'2. Diagnóstico'!A8) -> D07 | B8: =IF('2. Diagnóstico'!B8="","",'2. Diagnóstico'!B8) -> 2. Procesos y Operación | C8: =IF('2. Diagnóstico'!D8="","",'2. Diagnóstico'!D8) -> Los procesos se ejecutan de manera estandarizada entre áreas, turnos o personas? | D8: =IF('2. Diagnóstico'!K8="","",'2. Diagnóstico'!K8) -> 1 | F8: =IF(OR(D8="",E8=""),"",IF(AND(D8>=3,E8<=2),"Corto plazo",IF(AND(D8>=3,E8>2),"Mediano/Largo plazo",IF(D8<=0,"Sin brecha","Baja prioridad")))) | G8: =IF(D8="","",RANK(D8,$D$2:$D$37)+COUNTIF($D$2:D8,D8)-1) -> 3 | I8: =IFERROR(INDEX($C$2:$C$37,MATCH(6,$G$2:$G$37,0)),"") -> Existen lineamientos de uso responsable de IA y datos? | J8: =IFERROR(INDEX($B$2:$B$37,MATCH(6,$G$2:$G$37,0)),"") -> 3. Datos, Analítica e IA | K8: =IFERROR(INDEX($D$2:$D$37,MATCH(6,$G$2:$G$37,0)),"") -> 1
A9: =IF('2. Diagnóstico'!A9="","",'2. Diagnóstico'!A9) -> D08 | B9: =IF('2. Diagnóstico'!B9="","",'2. Diagnóstico'!B9) -> 2. Procesos y Operación | C9: =IF('2. Diagnóstico'!D9="","",'2. Diagnóstico'!D9) -> Qué proporción de los procesos clave tiene algún grado de automatización (RPA, BPM, workflow)? | D9: =IF('2. Diagnóstico'!K9="","",'2. Diagnóstico'!K9) -> 1 | F9: =IF(OR(D9="",E9=""),"",IF(AND(D9>=3,E9<=2),"Corto plazo",IF(AND(D9>=3,E9>2),"Mediano/Largo plazo",IF(D9<=0,"Sin brecha","Baja prioridad")))) | G9: =IF(D9="","",RANK(D9,$D$2:$D$37)+COUNTIF($D$2:D9,D9)-1) -> 4 | I9: =IFERROR(INDEX($C$2:$C$37,MATCH(7,$G$2:$G$37,0)),"") -> Existen políticas de control de acceso e identidad (MFA, roles)? | J9: =IFERROR(INDEX($B$2:$B$37,MATCH(7,$G$2:$G$37,0)),"") -> 5. Ciberseguridad y Riesgo | K9: =IFERROR(INDEX($D$2:$D$37,MATCH(7,$G$2:$G$37,0)),"") -> 1
A10: =IF('2. Diagnóstico'!A10="","",'2. Diagnóstico'!A10) -> D09 | B10: =IF('2. Diagnóstico'!B10="","",'2. Diagnóstico'!B10) -> 2. Procesos y Operación | C10: =IF('2. Diagnóstico'!D10="","",'2. Diagnóstico'!D10) -> Se miden tiempos de ciclo y cuellos de botella de los procesos? | D10: =IF('2. Diagnóstico'!K10="","",'2. Diagnóstico'!K10) -> 2 | F10: =IF(OR(D10="",E10=""),"",IF(AND(D10>=3,E10<=2),"Corto plazo",IF(AND(D10>=3,E10>2),"Mediano/Largo plazo",IF(D10<=0,"Sin brecha","Baja prioridad")))) | G10: =IF(D10="","",RANK(D10,$D$2:$D$37)+COUNTIF($D$2:D10,D10)-1) -> 1 | I10: =IFERROR(INDEX($C$2:$C$37,MATCH(8,$G$2:$G$37,0)),"") -> Existen líderes de cambio o agentes de transformación identificados? | J10: =IFERROR(INDEX($B$2:$B$37,MATCH(8,$G$2:$G$37,0)),"") -> 6. Cultura, Talento y Gestión del Cambio | K10: =IFERROR(INDEX($D$2:$D$37,MATCH(8,$G$2:$G$37,0)),"") -> 1
A11: =IF('2. Diagnóstico'!A11="","",'2. Diagnóstico'!A11) -> D10 | B11: =IF('2. Diagnóstico'!B11="","",'2. Diagnóstico'!B11) -> 2. Procesos y Operación | C11: =IF('2. Diagnóstico'!D11="","",'2. Diagnóstico'!D11) -> Existe un mecanismo formal de mejora continua de procesos? | D11: =IF('2. Diagnóstico'!K11="","",'2. Diagnóstico'!K11) -> 1 | F11: =IF(OR(D11="",E11=""),"",IF(AND(D11>=3,E11<=2),"Corto plazo",IF(AND(D11>=3,E11>2),"Mediano/Largo plazo",IF(D11<=0,"Sin brecha","Baja prioridad")))) | G11: =IF(D11="","",RANK(D11,$D$2:$D$37)+COUNTIF($D$2:D11,D11)-1) -> 5 | I11: =IFERROR(INDEX($C$2:$C$37,MATCH(9,$G$2:$G$37,0)),"") -> Se permiten pilotos o experimentos controlados con nuevas tecnologias? | J11: =IFERROR(INDEX($B$2:$B$37,MATCH(9,$G$2:$G$37,0)),"") -> 6. Cultura, Talento y Gestión del Cambio | K11: =IFERROR(INDEX($D$2:$D$37,MATCH(9,$G$2:$G$37,0)),"") -> 1
A12: =IF('2. Diagnóstico'!A12="","",'2. Diagnóstico'!A12) -> D11 | B12: =IF('2. Diagnóstico'!B12="","",'2. Diagnóstico'!B12) -> 3. Datos, Analítica e IA | C12: =IF('2. Diagnóstico'!D12="","",'2. Diagnóstico'!D12) -> Existe responsable o politica de datos en la organización? | D12: =IF('2. Diagnóstico'!K12="","",'2. Diagnóstico'!K12) -> 0 | F12: =IF(OR(D12="",E12=""),"",IF(AND(D12>=3,E12<=2),"Corto plazo",IF(AND(D12>=3,E12>2),"Mediano/Largo plazo",IF(D12<=0,"Sin brecha","Baja prioridad")))) | G12: =IF(D12="","",RANK(D12,$D$2:$D$37)+COUNTIF($D$2:D12,D12)-1) -> 19 | I12: =IFERROR(INDEX($C$2:$C$37,MATCH(10,$G$2:$G$37,0)),"") -> Existe comunicación estructurada sobre las iniciativas de transformación? | J12: =IFERROR(INDEX($B$2:$B$37,MATCH(10,$G$2:$G$37,0)),"") -> 6. Cultura, Talento y Gestión del Cambio | K12: =IFERROR(INDEX($D$2:$D$37,MATCH(10,$G$2:$G$37,0)),"") -> 1
A13: =IF('2. Diagnóstico'!A13="","",'2. Diagnóstico'!A13) -> D12 | B13: =IF('2. Diagnóstico'!B13="","",'2. Diagnóstico'!B13) -> 3. Datos, Analítica e IA | C13: =IF('2. Diagnóstico'!D13="","",'2. Diagnóstico'!D13) -> Se mide y gestiona la calidad de los datos (duplicados, completitud, exactitud)? | D13: =IF('2. Diagnóstico'!K13="","",'2. Diagnóstico'!K13) -> 2 | F13: =IF(OR(D13="",E13=""),"",IF(AND(D13>=3,E13<=2),"Corto plazo",IF(AND(D13>=3,E13>2),"Mediano/Largo plazo",IF(D13<=0,"Sin brecha","Baja prioridad")))) | G13: =IF(D13="","",RANK(D13,$D$2:$D$37)+COUNTIF($D$2:D13,D13)-1) -> 2
A14: =IF('2. Diagnóstico'!A14="","",'2. Diagnóstico'!A14) -> D13 | B14: =IF('2. Diagnóstico'!B14="","",'2. Diagnóstico'!B14) -> 3. Datos, Analítica e IA | C14: =IF('2. Diagnóstico'!D14="","",'2. Diagnóstico'!D14) -> Las decisiones de negocio se apoyan en reportes o dashboards de datos? | D14: =IF('2. Diagnóstico'!K14="","",'2. Diagnóstico'!K14) -> -1 | F14: =IF(OR(D14="",E14=""),"",IF(AND(D14>=3,E14<=2),"Corto plazo",IF(AND(D14>=3,E14>2),"Mediano/Largo plazo",IF(D14<=0,"Sin brecha","Baja prioridad")))) | G14: =IF(D14="","",RANK(D14,$D$2:$D$37)+COUNTIF($D$2:D14,D14)-1) -> 33
A15: =IF('2. Diagnóstico'!A15="","",'2. Diagnóstico'!A15) -> D14 | B15: =IF('2. Diagnóstico'!B15="","",'2. Diagnóstico'!B15) -> 3. Datos, Analítica e IA | C15: =IF('2. Diagnóstico'!D15="","",'2. Diagnóstico'!D15) -> Existe un repositorio centralizado de datos (DW o lake) frente a datos dispersos en Excel? | D15: =IF('2. Diagnóstico'!K15="","",'2. Diagnóstico'!K15) -> -1 | F15: =IF(OR(D15="",E15=""),"",IF(AND(D15>=3,E15<=2),"Corto plazo",IF(AND(D15>=3,E15>2),"Mediano/Largo plazo",IF(D15<=0,"Sin brecha","Baja prioridad")))) | G15: =IF(D15="","",RANK(D15,$D$2:$D$37)+COUNTIF($D$2:D15,D15)-1) -> 34
A16: =IF('2. Diagnóstico'!A16="","",'2. Diagnóstico'!A16) -> D15 | B16: =IF('2. Diagnóstico'!B16="","",'2. Diagnóstico'!B16) -> 3. Datos, Analítica e IA | C16: =IF('2. Diagnóstico'!D16="","",'2. Diagnóstico'!D16) -> La organización usa modelos o IA (incluida IA generativa) en algún proceso? | D16: =IF('2. Diagnóstico'!K16="","",'2. Diagnóstico'!K16) -> 0 | F16: =IF(OR(D16="",E16=""),"",IF(AND(D16>=3,E16<=2),"Corto plazo",IF(AND(D16>=3,E16>2),"Mediano/Largo plazo",IF(D16<=0,"Sin brecha","Baja prioridad")))) | G16: =IF(D16="","",RANK(D16,$D$2:$D$37)+COUNTIF($D$2:D16,D16)-1) -> 20
A17: =IF('2. Diagnóstico'!A17="","",'2. Diagnóstico'!A17) -> D16 | B17: =IF('2. Diagnóstico'!B17="","",'2. Diagnóstico'!B17) -> 3. Datos, Analítica e IA | C17: =IF('2. Diagnóstico'!D17="","",'2. Diagnóstico'!D17) -> Existen lineamientos de uso responsable de IA y datos? | D17: =IF('2. Diagnóstico'!K17="","",'2. Diagnóstico'!K17) -> 1 | F17: =IF(OR(D17="",E17=""),"",IF(AND(D17>=3,E17<=2),"Corto plazo",IF(AND(D17>=3,E17>2),"Mediano/Largo plazo",IF(D17<=0,"Sin brecha","Baja prioridad")))) | G17: =IF(D17="","",RANK(D17,$D$2:$D$37)+COUNTIF($D$2:D17,D17)-1) -> 6
A18: =IF('2. Diagnóstico'!A18="","",'2. Diagnóstico'!A18) -> D17 | B18: =IF('2. Diagnóstico'!B18="","",'2. Diagnóstico'!B18) -> 4. Arquitectura e Integración | C18: =IF('2. Diagnóstico'!D18="","",'2. Diagnóstico'!D18) -> Existe un inventario actualizado de sistemas y aplicaciones? | D18: =IF('2. Diagnóstico'!K18="","",'2. Diagnóstico'!K18) -> -1 | F18: =IF(OR(D18="",E18=""),"",IF(AND(D18>=3,E18<=2),"Corto plazo",IF(AND(D18>=3,E18>2),"Mediano/Largo plazo",IF(D18<=0,"Sin brecha","Baja prioridad")))) | G18: =IF(D18="","",RANK(D18,$D$2:$D$37)+COUNTIF($D$2:D18,D18)-1) -> 35
A19: =IF('2. Diagnóstico'!A19="","",'2. Diagnóstico'!A19) -> D18 | B19: =IF('2. Diagnóstico'!B19="","",'2. Diagnóstico'!B19) -> 4. Arquitectura e Integración | C19: =IF('2. Diagnóstico'!D19="","",'2. Diagnóstico'!D19) -> Qué tan actualizadas y soportadas están las aplicaciones críticas? | D19: =IF('2. Diagnóstico'!K19="","",'2. Diagnóstico'!K19) -> 0 | F19: =IF(OR(D19="",E19=""),"",IF(AND(D19>=3,E19<=2),"Corto plazo",IF(AND(D19>=3,E19>2),"Mediano/Largo plazo",IF(D19<=0,"Sin brecha","Baja prioridad")))) | G19: =IF(D19="","",RANK(D19,$D$2:$D$37)+COUNTIF($D$2:D19,D19)-1) -> 21
A20: =IF('2. Diagnóstico'!A20="","",'2. Diagnóstico'!A20) -> D19 | B20: =IF('2. Diagnóstico'!B20="","",'2. Diagnóstico'!B20) -> 4. Arquitectura e Integración | C20: =IF('2. Diagnóstico'!D20="","",'2. Diagnóstico'!D20) -> Qué proporción de la infraestructura está en la nube frente a on-premise? | D20: =IF('2. Diagnóstico'!K20="","",'2. Diagnóstico'!K20) -> 0 | F20: =IF(OR(D20="",E20=""),"",IF(AND(D20>=3,E20<=2),"Corto plazo",IF(AND(D20>=3,E20>2),"Mediano/Largo plazo",IF(D20<=0,"Sin brecha","Baja prioridad")))) | G20: =IF(D20="","",RANK(D20,$D$2:$D$37)+COUNTIF($D$2:D20,D20)-1) -> 22
A21: =IF('2. Diagnóstico'!A21="","",'2. Diagnóstico'!A21) -> D20 | B21: =IF('2. Diagnóstico'!B21="","",'2. Diagnóstico'!B21) -> 4. Arquitectura e Integración | C21: =IF('2. Diagnóstico'!D21="","",'2. Diagnóstico'!D21) -> Los sistemas se integran vía APIs/ESB o mediante cargas manuales de archivos? | D21: =IF('2. Diagnóstico'!K21="","",'2. Diagnóstico'!K21) -> 0 | F21: =IF(OR(D21="",E21=""),"",IF(AND(D21>=3,E21<=2),"Corto plazo",IF(AND(D21>=3,E21>2),"Mediano/Largo plazo",IF(D21<=0,"Sin brecha","Baja prioridad")))) | G21: =IF(D21="","",RANK(D21,$D$2:$D$37)+COUNTIF($D$2:D21,D21)-1) -> 23
A22: =IF('2. Diagnóstico'!A22="","",'2. Diagnóstico'!A22) -> D21 | B22: =IF('2. Diagnóstico'!B22="","",'2. Diagnóstico'!B22) -> 4. Arquitectura e Integración | C22: =IF('2. Diagnóstico'!D22="","",'2. Diagnóstico'!D22) -> La arquitectura soporta crecimiento en volumen o usuarios sin rediseño mayor? | D22: =IF('2. Diagnóstico'!K22="","",'2. Diagnóstico'!K22) -> 0 | F22: =IF(OR(D22="",E22=""),"",IF(AND(D22>=3,E22<=2),"Corto plazo",IF(AND(D22>=3,E22>2),"Mediano/Largo plazo",IF(D22<=0,"Sin brecha","Baja prioridad")))) | G22: =IF(D22="","",RANK(D22,$D$2:$D$37)+COUNTIF($D$2:D22,D22)-1) -> 24
A23: =IF('2. Diagnóstico'!A23="","",'2. Diagnóstico'!A23) -> D22 | B23: =IF('2. Diagnóstico'!B23="","",'2. Diagnóstico'!B23) -> 5. Ciberseguridad y Riesgo | C23: =IF('2. Diagnóstico'!D23="","",'2. Diagnóstico'!D23) -> Existen políticas de control de acceso e identidad (MFA, roles)? | D23: =IF('2. Diagnóstico'!K23="","",'2. Diagnóstico'!K23) -> 1 | F23: =IF(OR(D23="",E23=""),"",IF(AND(D23>=3,E23<=2),"Corto plazo",IF(AND(D23>=3,E23>2),"Mediano/Largo plazo",IF(D23<=0,"Sin brecha","Baja prioridad")))) | G23: =IF(D23="","",RANK(D23,$D$2:$D$37)+COUNTIF($D$2:D23,D23)-1) -> 7
A24: =IF('2. Diagnóstico'!A24="","",'2. Diagnóstico'!A24) -> D23 | B24: =IF('2. Diagnóstico'!B24="","",'2. Diagnóstico'!B24) -> 5. Ciberseguridad y Riesgo | C24: =IF('2. Diagnóstico'!D24="","",'2. Diagnóstico'!D24) -> Los datos sensibles están cifrados o protegidos adecuadamente? | D24: =IF('2. Diagnóstico'!K24="","",'2. Diagnóstico'!K24) -> 0 | F24: =IF(OR(D24="",E24=""),"",IF(AND(D24>=3,E24<=2),"Corto plazo",IF(AND(D24>=3,E24>2),"Mediano/Largo plazo",IF(D24<=0,"Sin brecha","Baja prioridad")))) | G24: =IF(D24="","",RANK(D24,$D$2:$D$37)+COUNTIF($D$2:D24,D24)-1) -> 25
... A37: =IF('2. Diagnóstico'!A37="","",'2. Diagnóstico'!A37) -> D36 | B37: =IF('2. Diagnóstico'!B37="","",'2. Diagnóstico'!B37) -> 7. Experiencia Digital | C37: =IF('2. Diagnóstico'!D37="","",'2. Diagnóstico'!D37) -> Los clientes pueden autogestionar solicitudes sin intervención humana? | D37: =IF('2. Diagnóstico'!K37="","",'2. Diagnóstico'!K37) -> 1 | F37: =IF(OR(D37="",E37=""),"",IF(AND(D37>=3,E37<=2),"Corto plazo",IF(AND(D37>=3,E37>2),"Mediano/Largo plazo",IF(D37<=0,"Sin brecha","Baja prioridad")))) | G37: =IF(D37="","",RANK(D37,$D$2:$D$37)+COUNTIF($D$2:D37,D37)-1) -> 13
A39: Nota: 'Brecha (Impacto)' se trae automáticamente de la pestaña 2. Complete solo 'Esfuerzo (1-5)'. La prioridad y el Rank se calculan solos.

Sheet Hoja1

Sheet 6. Iniciativas y Hoja de Ruta
A1: ID Brecha | B1: Dimensión | C1: Iniciativa | D1: Prioridad | E1: Responsable | F1: Plazo | G1: Estado
A2: D09 | B2: =IFERROR(INDEX('2. Diagnóstico'!$B$2:$B$37,MATCH(A2,'2. Diagnóstico'!$A$2:$A$37,0)),"") -> 2. Procesos y Operación | C2: Automatizar medición de tiempos de ciclo y cuellos de botella; definir indicadores, línea base y tablero de seguimiento. | D2: =IFERROR(INDEX('5. Brechas y Priorización'!$F$2:$F$37,MATCH(A2,'5. Brechas y Priorización'!$A$2:$A$37,0)),"") | E2: Líder de procesos + TI | F2: Corto plazo | G2: Por validar
A3: D12 | B3: =IFERROR(INDEX('2. Diagnóstico'!$B$2:$B$37,MATCH(A3,'2. Diagnóstico'!$A$2:$A$37,0)),"") -> 3. Datos, Analítica e IA | C3: Definir controles de calidad de datos: reglas de completitud, duplicados y exactitud, responsables y reporte periódico. | D3: =IFERROR(INDEX('5. Brechas y Priorización'!$F$2:$F$37,MATCH(A3,'5. Brechas y Priorización'!$A$2:$A$37,0)),"") | E3: Gobierno de datos + áreas dueñas | F3: Corto plazo | G3: Por validar
A4: D07 | B4: =IFERROR(INDEX('2. Diagnóstico'!$B$2:$B$37,MATCH(A4,'2. Diagnóstico'!$A$2:$A$37,0)),"") -> 2. Procesos y Operación | C4: Documentar y estandarizar los procesos prioritarios; publicar procedimientos y revisar cumplimiento. | D4: =IFERROR(INDEX('5. Brechas y Priorización'!$F$2:$F$37,MATCH(A4,'5. Brechas y Priorización'!$A$2:$A$37,0)),"") | E4: Dueños de proceso | F4: Corto plazo | G4: Por validar
A5: D08 | B5: =IFERROR(INDEX('2. Diagnóstico'!$B$2:$B$37,MATCH(A5,'2. Diagnóstico'!$A$2:$A$37,0)),"") -> 2. Procesos y Operación | C5: Seleccionar procesos repetitivos de alto volumen y diseñar pilotos de automatización con medición antes/después. | D5: =IFERROR(INDEX('5. Brechas y Priorización'!$F$2:$F$37,MATCH(A5,'5. Brechas y Priorización'!$A$2:$A$37,0)),"") | E5: Procesos + Automatización TI | F5: Corto plazo | G5: Por validar
A6: D16 | B6: =IFERROR(INDEX('2. Diagnóstico'!$B$2:$B$37,MATCH(A6,'2. Diagnóstico'!$A$2:$A$37,0)),"") -> 3. Datos, Analítica e IA | C6: Formalizar lineamientos de uso responsable de IA y datos, incluyendo privacidad, revisión humana y herramientas autorizadas. | D6: =IFERROR(INDEX('5. Brechas y Priorización'!$F$2:$F$37,MATCH(A6,'5. Brechas y Priorización'!$A$2:$A$37,0)),"") | E6: Seguridad TI + Jurídica + Datos | F6: Corto plazo | G6: Por validar
A7: D22 | B7: =IFERROR(INDEX('2. Diagnóstico'!$B$2:$B$37,MATCH(A7,'2. Diagnóstico'!$A$2:$A$37,0)),"") -> 5. Ciberseguridad y Riesgo | C7: Revisar cobertura de MFA, roles y recertificación de accesos; registrar excepciones y plan de cierre. | D7: =IFERROR(INDEX('5. Brechas y Priorización'!$F$2:$F$37,MATCH(A7,'5. Brechas y Priorización'!$A$2:$A$37,0)),"") | E7: Seguridad TI + Identidades | F7: Corto plazo | G7: Por validar
A8: D28 | B8: =IFERROR(INDEX('2. Diagnóstico'!$B$2:$B$37,MATCH(A8,'2. Diagnóstico'!$A$2:$A$37,0)),"") -> 6. Cultura, Talento y Gestión del Cambio | C8: Designar líderes de cambio por iniciativa y definir responsabilidades, indicadores y acompañamiento. | D8: =IFERROR(INDEX('5. Brechas y Priorización'!$F$2:$F$37,MATCH(A8,'5. Brechas y Priorización'!$A$2:$A$37,0)),"") | E8: Líderes de transformación | F8: Mediano plazo | G8: Por validar
A9: D30 | B9: =IFERROR(INDEX('2. Diagnóstico'!$B$2:$B$37,MATCH(A9,'2. Diagnóstico'!$A$2:$A$37,0)),"") -> 6. Cultura, Talento y Gestión del Cambio | C9: Establecer un método para pilotos tecnológicos con hipótesis, criterios de éxito, evaluación y decisión de escalamiento. | D9: =IFERROR(INDEX('5. Brechas y Priorización'!$F$2:$F$37,MATCH(A9,'5. Brechas y Priorización'!$A$2:$A$37,0)),"") | E9: Arquitectura TI + áreas usuarias | F9: Mediano plazo | G9: Por validar
A10: D31 | B10: =IFERROR(INDEX('2. Diagnóstico'!$B$2:$B$37,MATCH(A10,'2. Diagnóstico'!$A$2:$A$37,0)),"") -> 6. Cultura, Talento y Gestión del Cambio | C10: Implementar un plan de comunicación de iniciativas con audiencias, frecuencia, responsables y métricas de alcance. | D10: =IFERROR(INDEX('5. Brechas y Priorización'!$F$2:$F$37,MATCH(A10,'5. Brechas y Priorización'!$A$2:$A$37,0)),"") | E10: Comunicaciones + líderes de proyecto | F10: Mediano plazo | G10: Por validar
A11: D33 | B11: =IFERROR(INDEX('2. Diagnóstico'!$B$2:$B$37,MATCH(A11,'2. Diagnóstico'!$A$2:$A$37,0)),"") -> 7. Experiencia Digital | C11: Evaluar la necesidad de una vista unificada de usuarios/estudiantes/aliados, considerando sistemas existentes y privacidad. | D11: =IFERROR(INDEX('5. Brechas y Priorización'!$F$2:$F$37,MATCH(A11,'5. Brechas y Priorización'!$A$2:$A$37,0)),"") | E11: Arquitectura + Datos + áreas usuarias | F11: Mediano plazo | G11: Por validar
A12: D35 | B12: =IFERROR(INDEX('2. Diagnóstico'!$B$2:$B$37,MATCH(A12,'2. Diagnóstico'!$A$2:$A$37,0)),"") -> 7. Experiencia Digital | C12: Estandarizar medición de experiencia digital (CSAT/NPS o equivalente) y vincular resultados a planes de mejora. | D12: =IFERROR(INDEX('5. Brechas y Priorización'!$F$2:$F$37,MATCH(A12,'5. Brechas y Priorización'!$A$2:$A$37,0)),"") | E12: Experiencia digital + analítica | F12: Mediano plazo | G12: Por validar
A13: D36 | B13: =IFERROR(INDEX('2. Diagnóstico'!$B$2:$B$37,MATCH(A13,'2. Diagnóstico'!$A$2:$A$37,0)),"") -> 7. Experiencia Digital | C13: Identificar solicitudes aptas para autoservicio y priorizar un piloto con trazabilidad y medición de resolución. | D13: =IFERROR(INDEX('5. Brechas y Priorización'!$F$2:$F$37,MATCH(A13,'5. Brechas y Priorización'!$A$2:$A$37,0)),"") | E13: Servicios digitales + TI | F13: Mediano plazo | G13: Por validar
B14: =IFERROR(INDEX('2. Diagnóstico'!$B$2:$B$37,MATCH(A14,'2. Diagnóstico'!$A$2:$A$37,0)),"") | D14: =IFERROR(INDEX('5. Brechas y Priorización'!$F$2:$F$37,MATCH(A14,'5. Brechas y Priorización'!$A$2:$A$37,0)),"") | G14: No iniciada
B15: =IFERROR(INDEX('2. Diagnóstico'!$B$2:$B$37,MATCH(A15,'2. Diagnóstico'!$A$2:$A$37,0)),"") | D15: =IFERROR(INDEX('5. Brechas y Priorización'!$F$2:$F$37,MATCH(A15,'5. Brechas y Priorización'!$A$2:$A$37,0)),"") | G15: No iniciada
